barc4plots/__init__.py
barc4plots/barc4plots.py
barc4plots-2024.4.10.dist-info/LICENSE
barc4plots-2024.4.10.dist-info/METADATA
barc4plots-2024.4.10.dist-info/WHEEL
barc4plots-2024.4.10.dist-info/top_level.txt
barc4plots-2024.4.10.dist-info/RECORD
